pypwn/__init__.py
pypwn/core/__init__.py
pypwn/core/abstract/__init__.py
pypwn/core/abstract/module.py
pypwn/core/abstract/process.py
pypwn/core/abstract/target.py
pypwn/core/mixins/__init__.py
pypwn/core/mixins/elf.py
pypwn/core/mixins/libc.py
pypwn/core/mixins/rop.py
pypwn/core/protocols/__init__.py
pypwn/core/target/__init__.py
pypwn/core/target/local.py
pypwn/core/target/remote.py
pypwn/modules/__init__.py
pypwn/modules/exec_shell.py
pypwn/modules/find_function.py
pypwn/modules/find_offset.py
pypwn/modules/format_string_magic.py
pypwn/modules/get_libc_address.py
pypwn/utils/__init__.py
pypwn/utils/gdb_wrapper.py
pypwn/utils/libc_finder.py
pypwn-0.6.1.dist-info/LICENSE
pypwn-0.6.1.dist-info/METADATA
pypwn-0.6.1.dist-info/WHEEL
pypwn-0.6.1.dist-info/top_level.txt
pypwn-0.6.1.dist-info/RECORD
