Metadata-Version: 2.1
Name: pypwn
Version: 0.6.1
Summary: pwnlib wrappers for CTFs
Author-email: lim8en1 <lim8en1@proton.me>
Project-URL: Homepage, https://github.com/lim8en1/pypwn
Project-URL: Bug Tracker, https://github.com/lim8en1/pypwn/issues
Classifier: Programming Language :: Python :: 3
Classifier: License :: OSI Approved :: MIT License
Classifier: Operating System :: OS Independent
Requires-Python: >=3.10
License-File: LICENSE
Requires-Dist: pwntools
Requires-Dist: loguru
Requires-Dist: validators
